Metadata-Version: 2.1
Name: aindt-distributions
Version: 1.0
Summary: Gaussian and Binomial distributions
Author: Ana del Toro
Author-email: aindt.96@gmail.com
